{
  "('Alabama', 'Age (years)', '18 - 24')": 45.099998474121094,
  "('Alabama', 'Age (years)', '25 - 34')": 48.80000305175781,
  "('Alabama', 'Age (years)', '45 - 54')": 48.20000076293945,
  "('Alabama', 'Education', 'High school graduate')": 49.29999923706055,
  "('Alabama', 'Education', 'Less than high school')": 49.0,
  "('Alabama', 'Gender', 'Female')": 44.75,
  "('Alabama', 'Gender', 'Male')": 47.70000076293945,
  "('Alabama', 'Income', '$15,000 - $24,999')": 46.400001525878906,
  "('Alabama', 'Income', '$75,000 or greater')": 44.599998474121094,
  "('Alabama', 'Income', 'Less than $15,000')": 47.20000076293945,
  "('Alabama', 'Race/Ethnicity', 'American Indian/Alaska Native')": 30.600000381469727,
  "('Alabama', 'Race/Ethnicity', 'Asian')": 39.70000076293945,
  "('Alabama', 'Race/Ethnicity', 'Hawaiian/Pacific Islander')": 39.70000076293945,
  "('Alabama', 'Race/Ethnicity', 'Hispanic')": 33.79999923706055,
  "('Alabama', 'Race/Ethnicity', 'Non-Hispanic White')": 49.599998474121094,
  "('Alaska', 'Age (years)', '25 - 34')": 30.299999237060547,
  "('Alaska', 'Age (years)', '35 - 44')": 38.5,
  "('Alaska', 'Age (years)', '45 - 54')": 44.20000076293945,
  "('Alaska', 'Education', 'College graduate')": 30.69999885559082,
  "('Alaska', 'Gender', 'Female')": 29.399999618530273,
  "('Alaska', 'Gender', 'Male')": 44.29999923706055,
  "('Alaska', 'Income', '$15,000 - $24,999')": 44.79999923706055,
  "('Alaska', 'Income', '$25,000 - $34,999')": 47.400001525878906,
  "('Alaska', 'Income', '$50,000 - $74,999')": 34.0,
  "('Alaska', 'Income', '$75,000 or greater')": 38.900001525878906,
  "('Alaska', 'Income', 'Data not reported')": 46.54999923706055,
  "('Alaska', 'Income', 'Less than $15,000')": 51.5,
  "('Alaska', 'Race/Ethnicity', 'American Indian/Alaska Native')": 49.29999923706055,
  "('Alaska', 'Race/Ethnicity', 'Hawaiian/Pacific Islander')": 39.70000076293945,
  "('Alaska', 'Race/Ethnicity', 'Non-Hispanic White')": 34.5,
  "('Alaska', 'Race/Ethnicity', 'Other')": 39.70000076293945,
  "('Alaska', 'Total', 'Total')": 42.79999923706055,
  "('Arizona', 'Age (years)', '25 - 34')": 43.70000076293945,
  "('Arizona', 'Age (years)', '45 - 54')": 43.79999923706055,
  "('Arizona', 'Age (years)', '65 or older')": 34.349998474121094,
  "('Arizona', 'Education', 'High school graduate')": 43.05000305175781,
  "('Arizona', 'Education', 'Less than high school')": 42.20000076293945,
  "('Arizona', 'Gender', 'Female')": 33.29999923706055,
  "('Arizona', 'Income', '$15,000 - $24,999')": 39.20000076293945,
  "('Arizona', 'Income', '$25,000 - $34,999')": 37.900001525878906,
  "('Arizona', 'Income', '$35,000 - $49,999')": 44.099998474121094,
  "('Arizona', 'Income', '$50,000 - $74,999')": 37.29999923706055,
  "('Arizona', 'Income', '$75,000 or greater')": 43.599998474121094,
  "('Arizona', 'Income', 'Data not reported')": 38.400001525878906,
  "('Arizona', 'Race/Ethnicity', '2 or more races')": 35.70000076293945,
  "('Arizona', 'Race/Ethnicity', 'Asian')": 30.700000762939453,
  "('Arizona', 'Race/Ethnicity', 'Hawaiian/Pacific Islander')": 39.70000076293945,
  "('Arizona', 'Race/Ethnicity', 'Non-Hispanic Black')": 40.79999923706055,
  "('Arizona', 'Race/Ethnicity', 'Non-Hispanic White')": 41.400001525878906,
  "('Arkansas', 'Age (years)', '18 - 24')": 49.79999923706055,
  "('Arkansas', 'Age (years)', '35 - 44')": 44.5,
  "('Arkansas', 'Age (years)', '65 or older')": 43.099998474121094,
  "('Arkansas', 'Education', 'Less than high school')": 46.099998474121094,
  "('Arkansas', 'Gender', 'Male')": 46.400001525878906,
  "('Arkansas', 'Income', '$15,000 - $24,999')": 48.900001525878906,
  "('Arkansas', 'Income', '$50,000 - $74,999')": 47.0,
  "('Arkansas', 'Income', 'Data not reported')": 45.150001525878906,
  "('Arkansas', 'Income', 'Less than $15,000')": 52.94999694824219,
  "('Arkansas', 'Race/Ethnicity', '2 or more races')": 32.0,
  "('Arkansas', 'Race/Ethnicity', 'Hawaiian/Pacific Islander')": 39.70000076293945,
  "('Arkansas', 'Race/Ethnicity', 'Hispanic')": 29.899999618530273,
  "('Arkansas', 'Race/Ethnicity', 'Non-Hispanic Black')": 41.599998474121094,
  "('Arkansas', 'Race/Ethnicity', 'Other')": 39.70000076293945,
  "('Arkansas', 'Total', 'Total')": 44.70000076293945,
  "('California', 'Age (years)', '55 - 64')": 33.79999923706055,
  "('California', 'Education', 'High school graduate')": 38.54999923706055,
  "('California', 'Gender', 'Female')": 32.900001525878906,
  "('California', 'Income', '$25,000 - $34,999')": 33.29999923706055,
  "('California', 'Income', '$75,000 or greater')": 35.5,
  "('California', 'Income', 'Data not reported')": 34.900001525878906,
  "('California', 'Income', 'Less than $15,000')": 35.5,
  "('California', 'Race/Ethnicity', '2 or more races')": 35.44999694824219,
  "('California', 'Race/Ethnicity', 'American Indian/Alaska Native')": 42.39999771118164,
  "('California', 'Race/Ethnicity', 'Asian')": 36.0,
  "('California', 'Race/Ethnicity', 'Hawaiian/Pacific Islander')": 39.70000076293945,
  "('California', 'Race/Ethnicity', 'Non-Hispanic White')": 35.5,
  "('Colorado', 'Education', 'College graduate')": 31.600000381469727,
  "('Colorado', 'Education', 'Less than high school')": 36.900001525878906,
  "('Colorado', 'Gender', 'Male')": 40.25,
  "('Colorado', 'Income', '$25,000 - $34,999')": 34.599998474121094,
  "('Colorado', 'Income', '$35,000 - $49,999')": 39.79999923706055,
  "('Colorado', 'Income', '$75,000 or greater')": 39.099998474121094,
  "('Colorado', 'Income', 'Data not reported')": 35.70000076293945,
  "('Colorado', 'Race/Ethnicity', '2 or more races')": 39.400001525878906,
  "('Connecticut', 'Age (years)', '35 - 44')": 33.0,
  "('Connecticut', 'Age (years)', '45 - 54')": 35.5,
  "('Connecticut', 'Age (years)', '55 - 64')": 36.70000076293945,
  "('Connecticut', 'Education', 'College graduate')": 25.200000762939453,
  "('Connecticut', 'Income', '$15,000 - $24,999')": 32.599998474121094,
  "('Connecticut', 'Income', '$25,000 - $34,999')": 39.400001525878906,
  "('Connecticut', 'Income', '$35,000 - $49,999')": 37.79999923706055,
  "('Connecticut', 'Income', 'Less than $15,000')": 40.79999923706055,
  "('Connecticut', 'Race/Ethnicity', '2 or more races')": 31.5,
  "('Connecticut', 'Race/Ethnicity', 'American Indian/Alaska Native')": 39.70000076293945,
  "('Connecticut', 'Race/Ethnicity', 'Non-Hispanic Black')": 42.70000076293945,
  "('Connecticut', 'Race/Ethnicity', 'Non-Hispanic White')": 30.700000762939453,
  "('Delaware', 'Age (years)', '25 - 34')": 39.5,
  "('Delaware', 'Education', 'High school graduate')": 44.70000076293945,
  "('Delaware', 'Education', 'Some college or technical school')": 34.0,
  "('Delaware', 'Gender', 'Male')": 42.70000076293945,
  "('Delaware', 'Income', '$15,000 - $24,999')": 39.599998474121094,
  "('Delaware', 'Income', '$25,000 - $34,999')": 37.599998474121094,
  "('Delaware', 'Income', '$50,000 - $74,999')": 43.599998474121094,
  "('Delaware', 'Income', '$75,000 or greater')": 34.03333282470703,
  "('Delaware', 'Income', 'Data not reported')": 35.69999694824219,
  "('Delaware', 'Race/Ethnicity', 'American Indian/Alaska Native')": 39.70000076293945,
  "('Delaware', 'Race/Ethnicity', 'Non-Hispanic White')": 36.099998474121094,
  "('Delaware', 'Race/Ethnicity', 'Other')": 39.70000076293945,
  "('District of Columbia', 'Age (years)', '25 - 34')": 37.45000076293945,
  "('District of Columbia', 'Age (years)', '45 - 54')": 29.0,
  "('District of Columbia', 'Age (years)', '65 or older')": 23.5,
  "('District of Columbia', 'Education', 'College graduate')": 29.899999618530273,
  "('District of Columbia', 'Education', 'High school graduate')": 39.95000076293945,
  "('District of Columbia', 'Education', 'Some college or technical school')": 40.70000076293945,
  "('District of Columbia', 'Gender', 'Female')": 28.700000762939453,
  "('District of Columbia', 'Income', '$15,000 - $24,999')": 47.29999923706055,
  "('District of Columbia', 'Income', '$25,000 - $34,999')": 39.29999923706055,
  "('District of Columbia', 'Income', '$35,000 - $49,999')": 33.099998474121094,
  "('District of Columbia', 'Income', '$75,000 or greater')": 29.799999237060547,
  "('District of Columbia', 'Income', 'Less than $15,000')": 34.5,
  "('District of Columbia', 'Race/Ethnicity', 'American Indian/Alaska Native')": 39.70000076293945,
  "('District of Columbia', 'Race/Ethnicity', 'Asian')": 39.75,
  "('District of Columbia', 'Race/Ethnicity', 'Hispanic')": 37.29999923706055,
  "('District of Columbia', 'Race/Ethnicity', 'Non-Hispanic Black')": 35.79999923706055,
  "('District of Columbia', 'Race/Ethnicity', 'Non-Hispanic White')": 29.899999618530273,
  "('Florida', 'Age (years)', '18 - 24')": 39.70000076293945,
  "('Florida', 'Age (years)', '35 - 44')": 38.29999923706055,
  "('Florida', 'Age (years)', '55 - 64')": 38.849998474121094,
  "('Florida', 'Education', 'Less than high school')": 39.70000076293945,
  "('Florida', 'Education', 'Some college or technical school')": 37.099998474121094,
  "('Florida', 'Gender', 'Male')": 36.0,
  "('Florida', 'Income', '$50,000 - $74,999')": 39.70000076293945,
  "('Florida', 'Income', 'Data not reported')": 36.099998474121094,
  "('Florida', 'Race/Ethnicity', 'American Indian/Alaska Native')": 27.200000762939453,
  "('Florida', 'Race/Ethnicity', 'Asian')": 29.200000762939453,
  "('Florida', 'Race/Ethnicity', 'Non-Hispanic Black')": 36.25,
  "('Florida', 'Race/Ethnicity', 'Non-Hispanic White')": 35.400001525878906,
  "('Florida', 'Race/Ethnicity', 'Other')": 39.70000076293945,
  "('Florida', 'Total', 'Total')": 39.70000076293945,
  "('Georgia', 'Age (years)', '25 - 34')": 38.349998474121094,
  "('Georgia', 'Age (years)', '65 or older')": 36.20000076293945,
  "('Georgia', 'Education', 'High school graduate')": 44.900001525878906,
  "('Georgia', 'Education', 'Less than high school')": 44.349998474121094,
  "('Georgia', 'Education', 'Some college or technical school')": 43.900001525878906,
  "('Georgia', 'Gender', 'Female')": 35.400001525878906,
  "('Georgia', 'Income', '$15,000 - $24,999')": 43.599998474121094,
  "('Georgia', 'Income', '$35,000 - $49,999')": 40.20000076293945,
  "('Georgia', 'Income', '$50,000 - $74,999')": 41.0,
  "('Georgia', 'Income', 'Less than $15,000')": 45.70000076293945,
  "('Georgia', 'Race/Ethnicity', 'Asian')": 44.29999923706055,
  "('Georgia', 'Race/Ethnicity', 'Hispanic')": 30.299999237060547,
  "('Guam', 'Age (years)', '18 - 24')": 51.79999923706055,
  "('Guam', 'Age (years)', '25 - 34')": 52.79999923706055,
  "('Guam', 'Age (years)', '35 - 44')": 42.56666564941406,
  "('Guam', 'Age (years)', '55 - 64')": 40.400001525878906,
  "('Guam', 'Education', 'College graduate')": 43.900001525878906,
  "('Guam', 'Education', 'High school graduate')": 46.599998474121094,
  "('Guam', 'Education', 'Less than high school')": 38.20000076293945,
  "('Guam', 'Income', '$25,000 - $34,999')": 37.70000076293945,
  "('Guam', 'Income', '$35,000 - $49,999')": 47.400001525878906,
  "('Guam', 'Race/Ethnicity', '2 or more races')": 45.70000076293945,
  "('Guam', 'Race/Ethnicity', 'Non-Hispanic White')": 32.400001525878906,
  "('Guam', 'Race/Ethnicity', 'Other')": 39.70000076293945,
  "('Guam', 'Total', 'Total')": 49.0,
  "('Hawaii', 'Age (years)', '35 - 44')": 40.599998474121094,
  "('Hawaii', 'Age (years)', '55 - 64')": 42.900001525878906,
  "('Hawaii', 'Education', 'College graduate')": 33.94999694824219,
  "('Hawaii', 'Education', 'Some college or technical school')": 36.900001525878906,
  "('Hawaii', 'Gender', 'Female')": 37.95000076293945,
  "('Hawaii', 'Gender', 'Male')": 45.0,
  "('Hawaii', 'Income', '$15,000 - $24,999')": 35.29999923706055,
  "('Hawaii', 'Income', '$35,000 - $49,999')": 42.29999923706055,
  "('Hawaii', 'Income', '$75,000 or greater')": 36.20000076293945,
  "('Hawaii', 'Income', 'Data not reported')": 42.20000076293945,
  "('Hawaii', 'Race/Ethnicity', '2 or more races')": 39.70000076293945,
  "('Hawaii', 'Race/Ethnicity', 'American Indian/Alaska Native')": 39.70000076293945,
  "('Hawaii', 'Race/Ethnicity', 'Non-Hispanic Black')": 33.79999923706055,
  "('Hawaii', 'Race/Ethnicity', 'Other')": 39.70000076293945,
  "('Idaho', 'Age (years)', '25 - 34')": 35.0,
  "('Idaho', 'Age (years)', '45 - 54')": 43.599998474121094,
  "('Idaho', 'Age (years)', '65 or older')": 28.899999618530273,
  "('Idaho', 'Income', '$35,000 - $49,999')": 38.44999694824219,
  "('Idaho', 'Income', 'Data not reported')": 38.79999923706055,
  "('Idaho', 'Income', 'Less than $15,000')": 44.0,
  "('Idaho', 'Race/Ethnicity', '2 or more races')": 48.900001525878906,
  "('Idaho', 'Race/Ethnicity', 'American Indian/Alaska Native')": 39.70000076293945,
  "('Idaho', 'Race/Ethnicity', 'Non-Hispanic Black')": 39.70000076293945,
  "('Illinois', 'Age (years)', '18 - 24')": 39.599998474121094,
  "('Illinois', 'Age (years)', '25 - 34')": 42.599998474121094,
  "('Illinois', 'Age (years)', '45 - 54')": 31.600000381469727,
  "('Illinois', 'Age (years)', '65 or older')": 28.399999618530273,
  "('Illinois', 'Education', 'High school graduate')": 38.400001525878906,
  "('Illinois', 'Income', '$25,000 - $34,999')": 35.70000076293945,
  "('Illinois', 'Income', '$75,000 or greater')": 37.25,
  "('Illinois', 'Income', 'Less than $15,000')": 40.099998474121094,
  "('Illinois', 'Race/Ethnicity', '2 or more races')": 39.70000076293945,
  "('Illinois', 'Race/Ethnicity', 'Hawaiian/Pacific Islander')": 39.70000076293945,
  "('Illinois', 'Race/Ethnicity', 'Hispanic')": 32.79999923706055,
  "('Illinois', 'Race/Ethnicity', 'Non-Hispanic Black')": 37.29999923706055,
  "('Illinois', 'Race/Ethnicity', 'Non-Hispanic White')": 38.400001525878906,
  "('Illinois', 'Race/Ethnicity', 'Other')": 39.70000076293945,
  "('Indiana', 'Age (years)', '18 - 24')": 40.20000076293945,
  "('Indiana', 'Age (years)', '25 - 34')": 46.900001525878906,
  "('Indiana', 'Age (years)', '35 - 44')": 41.599998474121094,
  "('Indiana', 'Age (years)', '45 - 54')": 42.70000076293945,
  "('Indiana', 'Age (years)', '55 - 64')": 42.70000076293945,
  "('Indiana', 'Age (years)', '65 or older')": 35.20000076293945,
  "('Indiana', 'Education', 'College graduate')": 33.099998474121094,
  "('Indiana', 'Education', 'High school graduate')": 47.0,
  "('Indiana', 'Education', 'Less than high school')": 47.29999923706055,
  "('Indiana', 'Income', '$15,000 - $24,999')": 43.29999923706055,
  "('Indiana', 'Income', '$25,000 - $34,999')": 46.20000076293945,
  "('Indiana', 'Income', 'Data not reported')": 40.20000076293945,
  "('Indiana', 'Race/Ethnicity', '2 or more races')": 41.5,
  "('Indiana', 'Race/Ethnicity', 'American Indian/Alaska Native')": 34.5,
  "('Indiana', 'Race/Ethnicity', 'Asian')": 46.099998474121094,
  "('Indiana', 'Race/Ethnicity', 'Non-Hispanic Black')": 41.79999923706055,
  "('Indiana', 'Race/Ethnicity', 'Other')": 55.400001525878906,
  "('Iowa', 'Age (years)', '18 - 24')": 45.0,
  "('Iowa', 'Age (years)', '35 - 44')": 40.75,
  "('Iowa', 'Age (years)', '45 - 54')": 39.400001525878906,
  "('Iowa', 'Age (years)', '55 - 64')": 36.0,
  "('Iowa', 'Age (years)', '65 or older')": 31.700000762939453,
  "('Iowa', 'Education', 'College graduate')": 26.899999618530273,
  "('Iowa', 'Education', 'Less than high school')": 39.099998474121094,
  "('Iowa', 'Education', 'Some college or technical school')": 36.900001525878906,
  "('Iowa', 'Gender', 'Female')": 37.20000076293945,
  "('Iowa', 'Gender', 'Male')": 45.5,
  "('Iowa', 'Income', '$15,000 - $24,999')": 45.20000076293945,
  "('Iowa', 'Income', '$75,000 or greater')": 31.700000762939453,
  "('Iowa', 'Income', 'Data not reported')": 37.79999923706055,
  "('Iowa', 'Race/Ethnicity', '2 or more races')": 41.400001525878906,
  "('Iowa', 'Race/Ethnicity', 'American Indian/Alaska Native')": 45.5,
  "('Iowa', 'Race/Ethnicity', 'Hawaiian/Pacific Islander')": 39.70000076293945,
  "('Iowa', 'Race/Ethnicity', 'Non-Hispanic Black')": 38.79999923706055,
  "('Iowa', 'Race/Ethnicity', 'Non-Hispanic White')": 40.400001525878906,
  "('Iowa', 'Race/Ethnicity', 'Other')": 39.70000076293945,
  "('Iowa', 'Total', 'Total')": 38.04999923706055,
  "('Kansas', 'Age (years)', '35 - 44')": 38.400001525878906,
  "('Kansas', 'Age (years)', '45 - 54')": 41.0,
  "('Kansas', 'Education', 'College graduate')": 30.200000762939453,
  "('Kansas', 'Education', 'Less than high school')": 47.70000076293945,
  "('Kansas', 'Education', 'Some college or technical school')": 43.29999923706055,
  "('Kansas', 'Income', '$25,000 - $34,999')": 45.0,
  "('Kansas', 'Income', '$35,000 - $49,999')": 38.099998474121094,
  "('Kansas', 'Race/Ethnicity', '2 or more races')": 44.70000076293945,
  "('Kansas', 'Race/Ethnicity', 'Asian')": 30.700000762939453,
  "('Kansas', 'Race/Ethnicity', 'Hawaiian/Pacific Islander')": 39.70000076293945,
  "('Kansas', 'Race/Ethnicity', 'Non-Hispanic Black')": 42.599998474121094,
  "('Kansas', 'Race/Ethnicity', 'Non-Hispanic White')": 39.55000305175781,
  "('Kansas', 'Total', 'Total')": 41.400001525878906,
  "('Kentucky', 'Age (years)', '45 - 54')": 45.5,
  "('Kentucky', 'Age (years)', '65 or older')": 38.5,
  "('Kentucky', 'Education', 'College graduate')": 38.400001525878906,
  "('Kentucky', 'Education', 'Less than high school')": 50.29999923706055,
  "('Kentucky', 'Education', 'Some college or technical school')": 45.79999923706055,
  "('Kentucky', 'Gender', 'Female')": 42.400001525878906,
  "('Kentucky', 'Income', '$35,000 - $49,999')": 41.29999923706055,
  "('Kentucky', 'Race/Ethnicity', 'Asian')": 39.70000076293945,
  "('Kentucky', 'Race/Ethnicity', 'Hawaiian/Pacific Islander')": 39.70000076293945,
  "('Kentucky', 'Race/Ethnicity', 'Non-Hispanic Black')": 42.150001525878906,
  "('Kentucky', 'Race/Ethnicity', 'Non-Hispanic White')": 45.29999923706055,
  "('Kentucky', 'Total', 'Total')": 45.400001525878906,
  "('Louisiana', 'Age (years)', '25 - 34')": 53.29999923706055,
  "('Louisiana', 'Age (years)', '35 - 44')": 51.0,
  "('Louisiana', 'Age (years)', '45 - 54')": 50.349998474121094,
  "('Louisiana', 'Age (years)', '65 or older')": 43.0,
  "('Louisiana', 'Education', 'High school graduate')": 46.900001525878906,
  "('Louisiana', 'Education', 'Some college or technical school')": 46.0,
  "('Louisiana', 'Gender', 'Female')": 44.75,
  "('Louisiana', 'Income', '$35,000 - $49,999')": 43.5,
  "('Louisiana', 'Income', 'Data not reported')": 42.20000076293945,
  "('Louisiana', 'Race/Ethnicity', 'Asian')": 39.70000076293945,
  "('Louisiana', 'Race/Ethnicity', 'Hawaiian/Pacific Islander')": 39.70000076293945,
  "('Louisiana', 'Total', 'Total')": 46.099998474121094,
  "('Maine', 'Age (years)', '18 - 24')": 30.600000381469727,
  "('Maine', 'Age (years)', '25 - 34')": 38.599998474121094,
  "('Maine', 'Age (years)', '35 - 44')": 32.79999923706055,
  "('Maine', 'Age (years)', '45 - 54')": 32.70000076293945,
  "('Maine', 'Age (years)', '55 - 64')": 38.5,
  "('Maine', 'Age (years)', '65 or older')": 26.799999237060547,
  "('Maine', 'Education', 'High school graduate')": 39.79999923706055,
  "('Maine', 'Education', 'Some college or technical school')": 37.29999923706055,
  "('Maine', 'Gender', 'Female')": 31.799999237060547,
  "('Maine', 'Gender', 'Male')": 38.5,
  "('Maine', 'Income', '$25,000 - $34,999')": 40.79999923706055,
  "('Maine', 'Income', '$50,000 - $74,999')": 35.099998474121094,
  "('Maine', 'Income', 'Less than $15,000')": 44.79999923706055,
  "('Maine', 'Race/Ethnicity', '2 or more races')": 29.399999618530273,
  "('Maine', 'Race/Ethnicity', 'Asian')": 39.70000076293945,
  "('Maine', 'Race/Ethnicity', 'Non-Hispanic White')": 34.900001525878906,
  "('Maine', 'Total', 'Total')": 35.0,
  "('Maryland', 'Age (years)', '25 - 34')": 34.099998474121094,
  "('Maryland', 'Age (years)', '35 - 44')": 33.5,
  "('Maryland', 'Age (years)', '45 - 54')": 37.150001525878906,
  "('Maryland', 'Education', 'High school graduate')": 42.099998474121094,
  "('Maryland', 'Education', 'Less than high school')": 36.20000076293945,
  "('Maryland', 'Income', '$25,000 - $34,999')": 35.0,
  "('Maryland', 'Income', '$50,000 - $74,999')": 39.099998474121094,
  "('Maryland', 'Income', '$75,000 or greater')": 33.79999923706055,
  "('Maryland', 'Income', 'Data not reported')": 35.5,
  "('Maryland', 'Race/Ethnicity', 'American Indian/Alaska Native')": 26.799999237060547,
  "('Maryland', 'Race/Ethnicity', 'Asian')": 30.850000381469727,
  "('Maryland', 'Race/Ethnicity', 'Hawaiian/Pacific Islander')": 39.70000076293945,
  "('Massachusetts', 'Age (years)', '55 - 64')": 31.600000381469727,
  "('Massachusetts', 'Education', 'Some college or technical school')": 33.599998474121094,
  "('Massachusetts', 'Gender', 'Female')": 31.400001525878906,
  "('Massachusetts', 'Income', '$15,000 - $24,999')": 34.70000076293945,
  "('Massachusetts', 'Income', '$25,000 - $34,999')": 36.5,
  "('Massachusetts', 'Income', '$50,000 - $74,999')": 38.5,
  "('Massachusetts', 'Income', 'Data not reported')": 35.20000076293945,
  "('Massachusetts', 'Race/Ethnicity', 'American Indian/Alaska Native')": 39.70000076293945,
  "('Michigan', 'Age (years)', '25 - 34')": 38.599998474121094,
  "('Michigan', 'Age (years)', '35 - 44')": 38.75,
  "('Michigan', 'Education', 'College graduate')": 28.200000762939453,
  "('Michigan', 'Education', 'Less than high school')": 48.70000076293945,
  "('Michigan', 'Gender', 'Female')": 36.5,
  "('Michigan', 'Income', '$25,000 - $34,999')": 41.04999923706055,
  "('Michigan', 'Income', '$75,000 or greater')": 35.400001525878906,
  "('Michigan', 'Income', 'Less than $15,000')": 47.79999923706055,
  "('Michigan', 'Race/Ethnicity', '2 or more races')": 39.400001525878906,
  "('Michigan', 'Race/Ethnicity', 'Asian')": 40.33333206176758,
  "('Michigan', 'Race/Ethnicity', 'Hawaiian/Pacific Islander')": 39.70000076293945,
  "('Michigan', 'Race/Ethnicity', 'Non-Hispanic White')": 39.20000076293945,
  "('Michigan', 'Total', 'Total')": 36.400001525878906,
  "('Minnesota', 'Age (years)', '18 - 24')": 44.099998474121094,
  "('Minnesota', 'Age (years)', '35 - 44')": 31.799999237060547,
  "('Minnesota', 'Age (years)', '45 - 54')": 37.0,
  "('Minnesota', 'Age (years)', '55 - 64')": 33.900001525878906,
  "('Minnesota', 'Gender', 'Female')": 32.599998474121094,
  "('Minnesota', 'Income', '$15,000 - $24,999')": 37.79999923706055,
  "('Minnesota', 'Income', '$25,000 - $34,999')": 38.849998474121094,
  "('Minnesota', 'Income', '$75,000 or greater')": 36.20000076293945,
  "('Minnesota', 'Income', 'Data not reported')": 36.599998474121094,
  "('Minnesota', 'Race/Ethnicity', 'American Indian/Alaska Native')": 41.900001525878906,
  "('Minnesota', 'Race/Ethnicity', 'Hawaiian/Pacific Islander')": 39.70000076293945,
  "('Minnesota', 'Race/Ethnicity', 'Hispanic')": 35.29999923706055,
  "('Minnesota', 'Race/Ethnicity', 'Non-Hispanic Black')": 41.20000076293945,
  "('Minnesota', 'Race/Ethnicity', 'Non-Hispanic White')": 35.29999923706055,
  "('Minnesota', 'Race/Ethnicity', 'Other')": 39.70000076293945,
  "('Minnesota', 'Total', 'Total')": 32.29999923706055,
  "('Mississippi', 'Age (years)', '25 - 34')": 47.599998474121094,
  "('Mississippi', 'Age (years)', '55 - 64')": 54.29999923706055,
  "('Mississippi', 'Age (years)', '65 or older')": 41.099998474121094,
  "('Mississippi', 'Education', 'Less than high school')": 50.19999694824219,
  "('Mississippi', 'Education', 'Some college or technical school')": 43.099998474121094,
  "('Mississippi', 'Income', '$25,000 - $34,999')": 42.0,
  "('Mississippi', 'Race/Ethnicity', 'American Indian/Alaska Native')": 39.70000076293945,
  "('Mississippi', 'Race/Ethnicity', 'Hawaiian/Pacific Islander')": 39.70000076293945,
  "('Mississippi', 'Race/Ethnicity', 'Non-Hispanic White')": 48.099998474121094,
  "('Missouri', 'Age (years)', '18 - 24')": 43.0,
  "('Missouri', 'Age (years)', '55 - 64')": 46.099998474121094,
  "('Missouri', 'Education', 'College graduate')": 31.200000762939453,
  "('Missouri', 'Education', 'High school graduate')": 44.599998474121094,
  "('Missouri', 'Gender', 'Male')": 45.733333587646484,
  "('Missouri', 'Income', '$15,000 - $24,999')": 48.150001525878906,
  "('Missouri', 'Income', '$25,000 - $34,999')": 41.400001525878906,
  "('Missouri', 'Income', '$75,000 or greater')": 42.79999923706055,
  "('Missouri', 'Income', 'Less than $15,000')": 45.900001525878906,
  "('Missouri', 'Race/Ethnicity', 'American Indian/Alaska Native')": 39.349998474121094,
  "('Missouri', 'Race/Ethnicity', 'Hispanic')": 33.70000076293945,
  "('Missouri', 'Race/Ethnicity', 'Other')": 39.70000076293945,
  "('Missouri', 'Total', 'Total')": 43.400001525878906,
  "('Montana', 'Age (years)', '18 - 24')": 44.25,
  "('Montana', 'Age (years)', '25 - 34')": 43.400001525878906,
  "('Montana', 'Age (years)', '35 - 44')": 39.29999923706055,
  "('Montana', 'Age (years)', '45 - 54')": 44.099998474121094,
  "('Montana', 'Age (years)', '65 or older')": 29.100000381469727,
  "('Montana', 'Education', 'High school graduate')": 42.099998474121094,
  "('Montana', 'Gender', 'Male')": 42.20000076293945,
  "('Montana', 'Income', '$15,000 - $24,999')": 39.900001525878906,
  "('Montana', 'Income', '$25,000 - $34,999')": 42.400001525878906,
  "('Montana', 'Income', '$35,000 - $49,999')": 40.44999694824219,
  "('Montana', 'Income', 'Data not reported')": 35.0,
  "('Montana', 'Race/Ethnicity', '2 or more races')": 40.0,
  "('Montana', 'Race/Ethnicity', 'American Indian/Alaska Native')": 40.099998474121094,
  "('Montana', 'Race/Ethnicity', 'Asian')": 39.70000076293945,
  "('Montana', 'Race/Ethnicity', 'Non-Hispanic Black')": 39.70000076293945,
  "('Montana', 'Race/Ethnicity', 'Non-Hispanic White')": 36.29999923706055,
  "('Montana', 'Race/Ethnicity', 'Other')": 39.70000076293945,
  "('Montana', 'Total', 'Total')": 36.400001525878906,
  "('National', 'Age (years)', '25 - 34')": 42.79999923706055,
  "('National', 'Age (years)', '35 - 44')": 39.5,
  "('National', 'Age (years)', '55 - 64')": 38.099998474121094,
  "('National', 'Age (years)', '65 or older')": 31.600000381469727,
  "('National', 'Gender', 'Female')": 32.900001525878906,
  "('National', 'Gender', 'Male')": 42.900001525878906,
  "('National', 'Income', '$15,000 - $24,999')": 42.099998474121094,
  "('National', 'Income', '$25,000 - $34,999')": 37.900001525878906,
  "('National', 'Income', '$50,000 - $74,999')": 35.400001525878906,
  "('National', 'Race/Ethnicity', '2 or more races')": 39.900001525878906,
  "('National', 'Race/Ethnicity', 'American Indian/Alaska Native')": 41.599998474121094,
  "('National', 'Race/Ethnicity', 'Hawaiian/Pacific Islander')": 39.400001525878906,
  "('National', 'Race/Ethnicity', 'Non-Hispanic White')": 39.400001525878906,
  "('Nebraska', 'Age (years)', '18 - 24')": 45.900001525878906,
  "('Nebraska', 'Age (years)', '35 - 44')": 38.79999923706055,
  "('Nebraska', 'Age (years)', '45 - 54')": 46.29999923706055,
  "('Nebraska', 'Age (years)', '55 - 64')": 40.20000076293945,
  "('Nebraska', 'Age (years)', '65 or older')": 30.5,
  "('Nebraska', 'Education', 'Less than high school')": 40.70000076293945,
  "('Nebraska', 'Education', 'Some college or technical school')": 41.75,
  "('Nebraska', 'Gender', 'Female')": 35.099998474121094,
  "('Nebraska', 'Income', '$15,000 - $24,999')": 37.79999923706055,
  "('Nebraska', 'Income', '$35,000 - $49,999')": 44.79999923706055,
  "('Nebraska', 'Income', '$50,000 - $74,999')": 38.400001525878906,
  "('Nebraska', 'Race/Ethnicity', '2 or more races')": 46.599998474121094,
  "('Nebraska', 'Race/Ethnicity', 'American Indian/Alaska Native')": 44.79999923706055,
  "('Nebraska', 'Race/Ethnicity', 'Non-Hispanic Black')": 45.19999694824219,
  "('Nebraska', 'Race/Ethnicity', 'Non-Hispanic White')": 37.0,
  "('Nebraska', 'Race/Ethnicity', 'Other')": 39.70000076293945,
  "('Nebraska', 'Total', 'Total')": 42.70000076293945,
  "('Nevada', 'Age (years)', '18 - 24')": 44.29999923706055,
  "('Nevada', 'Age (years)', '25 - 34')": 49.900001525878906,
  "('Nevada', 'Age (years)', '45 - 54')": 41.79999923706055,
  "('Nevada', 'Education', 'Less than high school')": 41.20000076293945,
  "('Nevada', 'Education', 'Some college or technical school')": 42.79999923706055,
  "('Nevada', 'Gender', 'Male')": 41.29999923706055,
  "('Nevada', 'Income', '$25,000 - $34,999')": 42.25,
  "('Nevada', 'Income', '$50,000 - $74,999')": 46.29999923706055,
  "('Nevada', 'Income', 'Data not reported')": 40.70000076293945,
  "('Nevada', 'Income', 'Less than $15,000')": 48.70000076293945,
  "('Nevada', 'Race/Ethnicity', 'American Indian/Alaska Native')": 46.70000076293945,
  "('Nevada', 'Race/Ethnicity', 'Asian')": 50.20000076293945,
  "('Nevada', 'Race/Ethnicity', 'Hispanic')": 29.700000762939453,
  "('New Hampshire', 'Age (years)', '45 - 54')": 35.54999923706055,
  "('New Hampshire', 'Age (years)', '55 - 64')": 32.29999923706055,
  "('New Hampshire', 'Age (years)', '65 or older')": 27.299999237060547,
  "('New Hampshire', 'Education', 'College graduate')": 28.899999618530273,
  "('New Hampshire', 'Gender', 'Female')": 33.20000076293945,
  "('New Hampshire', 'Gender', 'Male')": 36.5,
  "('New Hampshire', 'Income', '$35,000 - $49,999')": 36.900001525878906,
  "('New Hampshire', 'Income', 'Less than $15,000')": 39.099998474121094,
  "('New Hampshire', 'Race/Ethnicity', 'Asian')": 39.70000076293945,
  "('New Hampshire', 'Race/Ethnicity', 'Hawaiian/Pacific Islander')": 39.70000076293945,
  "('New Hampshire', 'Race/Ethnicity', 'Non-Hispanic Black')": 39.70000076293945,
  "('New Hampshire', 'Race/Ethnicity', 'Non-Hispanic White')": 32.75,
  "('New Hampshire', 'Total', 'Total')": 33.19999694824219,
  "('New Jersey', 'Age (years)', '25 - 34')": 40.099998474121094,
  "('New Jersey', 'Age (years)', '35 - 44')": 35.599998474121094,
  "('New Jersey', 'Age (years)', '65 or older')": 31.299999237060547,
  "('New Jersey', 'Education', 'High school graduate')": 38.79999923706055,
  "('New Jersey', 'Education', 'Less than high school')": 37.20000076293945,
  "('New Jersey', 'Gender', 'Male')": 39.20000076293945,
  "('New Jersey', 'Income', '$25,000 - $34,999')": 37.79999923706055,
  "('New Jersey', 'Income', 'Data not reported')": 32.79999923706055,
  "('New Jersey', 'Income', 'Less than $15,000')": 46.0,
  "('New Jersey', 'Race/Ethnicity', 'Asian')": 29.399999618530273,
  "('New Jersey', 'Race/Ethnicity', 'Non-Hispanic Black')": 39.400001525878906,
  "('New Jersey', 'Race/Ethnicity', 'Non-Hispanic White')": 35.79999923706055,
  "('New Jersey', 'Race/Ethnicity', 'Other')": 24.399999618530273,
  "('New Mexico', 'Age (years)', '18 - 24')": 43.900001525878906,
  "('New Mexico', 'Age (years)', '25 - 34')": 43.400001525878906,
  "('New Mexico', 'Age (years)', '35 - 44')": 41.75,
  "('New Mexico', 'Education', 'Less than high school')": 40.900001525878906,
  "('New Mexico', 'Education', 'Some college or technical school')": 39.099998474121094,
  "('New Mexico', 'Gender', 'Male')": 43.900001525878906,
  "('New Mexico', 'Income', '$25,000 - $34,999')": 37.5,
  "('New Mexico', 'Income', '$35,000 - $49,999')": 39.599998474121094,
  "('New Mexico', 'Income', '$75,000 or greater')": 42.29999923706055,
  "('New Mexico', 'Race/Ethnicity', 'American Indian/Alaska Native')": 33.70000076293945,
  "('New Mexico', 'Race/Ethnicity', 'Hispanic')": 41.29999923706055,
  "('New Mexico', 'Race/Ethnicity', 'Non-Hispanic White')": 42.0,
  "('New Mexico', 'Total', 'Total')": 40.25,
  "('New York', 'Age (years)', '45 - 54')": 35.70000076293945,
  "('New York', 'Age (years)', '65 or older')": 26.899999618530273,
  "('New York', 'Education', 'Less than high school')": 37.45000076293945,
  "('New York', 'Gender', 'Male')": 39.0,
  "('New York', 'Income', '$35,000 - $49,999')": 38.0,
  "('New York', 'Income', 'Data not reported')": 35.099998474121094,
  "('New York', 'Income', 'Less than $15,000')": 41.900001525878906,
  "('New York', 'Race/Ethnicity', 'American Indian/Alaska Native')": 36.20000076293945,
  "('New York', 'Race/Ethnicity', 'Asian')": 32.599998474121094,
  "('New York', 'Race/Ethnicity', 'Hispanic')": 38.099998474121094,
  "('New York', 'Race/Ethnicity', 'Non-Hispanic Black')": 37.599998474121094,
  "('New York', 'Race/Ethnicity', 'Non-Hispanic White')": 36.400001525878906,
  "('North Carolina', 'Age (years)', '18 - 24')": 40.900001525878906,
  "('North Carolina', 'Age (years)', '25 - 34')": 39.400001525878906,
  "('North Carolina', 'Age (years)', '45 - 54')": 41.79999923706055,
  "('North Carolina', 'Age (years)', '55 - 64')": 40.900001525878906,
  "('North Carolina', 'Age (years)', '65 or older')": 37.400001525878906,
  "('North Carolina', 'Income', '$15,000 - $24,999')": 41.0,
  "('North Carolina', 'Income', '$35,000 - $49,999')": 40.900001525878906,
  "('North Carolina', 'Income', '$50,000 - $74,999')": 33.400001525878906,
  "('North Carolina', 'Income', 'Less than $15,000')": 46.0,
  "('North Carolina', 'Race/Ethnicity', 'American Indian/Alaska Native')": 48.5,
  "('North Carolina', 'Race/Ethnicity', 'Asian')": 39.70000076293945,
  "('North Carolina', 'Race/Ethnicity', 'Hawaiian/Pacific Islander')": 39.70000076293945,
  "('North Carolina', 'Race/Ethnicity', 'Non-Hispanic White')": 39.0,
  "('North Carolina', 'Total', 'Total')": 40.400001525878906,
  "('North Dakota', 'Age (years)', '35 - 44')": 42.54999923706055,
  "('North Dakota', 'Income', '$15,000 - $24,999')": 41.29999923706055,
  "('North Dakota', 'Income', '$50,000 - $74,999')": 40.599998474121094,
  "('North Dakota', 'Income', '$75,000 or greater')": 44.0,
  "('North Dakota', 'Race/Ethnicity', '2 or more races')": 29.299999237060547,
  "('North Dakota', 'Race/Ethnicity', 'American Indian/Alaska Native')": 46.400001525878906,
  "('North Dakota', 'Race/Ethnicity', 'Asian')": 39.70000076293945,
  "('North Dakota', 'Race/Ethnicity', 'Hawaiian/Pacific Islander')": 39.70000076293945,
  "('North Dakota', 'Race/Ethnicity', 'Hispanic')": 16.799999237060547,
  "('North Dakota', 'Race/Ethnicity', 'Other')": 39.70000076293945,
  "('Ohio', 'Age (years)', '18 - 24')": 37.599998474121094,
  "('Ohio', 'Age (years)', '35 - 44')": 44.20000076293945,
  "('Ohio', 'Age (years)', '45 - 54')": 41.79999923706055,
  "('Ohio', 'Education', 'College graduate')": 35.599998474121094,
  "('Ohio', 'Education', 'High school graduate')": 47.20000076293945,
  "('Ohio', 'Education', 'Less than high school')": 49.5,
  "('Ohio', 'Gender', 'Female')": 34.20000076293945,
  "('Ohio', 'Income', '$35,000 - $49,999')": 43.29999923706055,
  "('Ohio', 'Income', '$50,000 - $74,999')": 40.0,
  "('Ohio', 'Income', 'Data not reported')": 41.5,
  "('Ohio', 'Race/Ethnicity', 'American Indian/Alaska Native')": 48.900001525878906,
  "('Ohio', 'Race/Ethnicity', 'Asian')": 31.899999618530273,
  "('Ohio', 'Race/Ethnicity', 'Hawaiian/Pacific Islander')": 39.70000076293945,
  "('Ohio', 'Race/Ethnicity', 'Non-Hispanic White')": 42.599998474121094,
  "('Ohio', 'Race/Ethnicity', 'Other')": 39.70000076293945,
  "('Oklahoma', 'Age (years)', '25 - 34')": 53.099998474121094,
  "('Oklahoma', 'Age (years)', '35 - 44')": 49.29999923706055,
  "('Oklahoma', 'Age (years)', '45 - 54')": 52.70000076293945,
  "('Oklahoma', 'Education', 'College graduate')": 43.20000076293945,
  "('Oklahoma', 'Education', 'Some college or technical school')": 45.70000076293945,
  "('Oklahoma', 'Gender', 'Female')": 44.099998474121094,
  "('Oklahoma', 'Gender', 'Male')": 47.70000076293945,
  "('Oklahoma', 'Race/Ethnicity', 'Asian')": 38.05000305175781,
  "('Oklahoma', 'Race/Ethnicity', 'Hispanic')": 42.20000076293945,
  "('Oklahoma', 'Race/Ethnicity', 'Non-Hispanic White')": 45.900001525878906,
  "('Oregon', 'Age (years)', '45 - 54')": 34.19999694824219,
  "('Oregon', 'Age (years)', '55 - 64')": 36.79999923706055,
  "('Oregon', 'Education', 'Less than high school')": 41.79999923706055,
  "('Oregon', 'Education', 'Some college or technical school')": 31.600000381469727,
  "('Oregon', 'Gender', 'Female')": 31.450000762939453,
  "('Oregon', 'Gender', 'Male')": 41.900001525878906,
  "('Oregon', 'Income', '$15,000 - $24,999')": 40.79999923706055,
  "('Oregon', 'Income', 'Data not reported')": 37.20000076293945,
  "('Oregon', 'Race/Ethnicity', '2 or more races')": 49.79999923706055,
  "('Oregon', 'Race/Ethnicity', 'Asian')": 41.866668701171875,
  "('Oregon', 'Race/Ethnicity', 'Hawaiian/Pacific Islander')": 39.70000076293945,
  "('Oregon', 'Race/Ethnicity', 'Hispanic')": 39.25,
  "('Pennsylvania', 'Age (years)', '18 - 24')": 46.29999923706055,
  "('Pennsylvania', 'Education', 'High school graduate')": 41.29999923706055,
  "('Pennsylvania', 'Education', 'Some college or technical school')": 40.79999923706055,
  "('Pennsylvania', 'Gender', 'Male')": 39.19999694824219,
  "('Pennsylvania', 'Income', '$75,000 or greater')": 34.150001525878906,
  "('Pennsylvania', 'Income', 'Data not reported')": 36.29999923706055,
  "('Pennsylvania', 'Race/Ethnicity', 'American Indian/Alaska Native')": 39.70000076293945,
  "('Pennsylvania', 'Race/Ethnicity', 'Non-Hispanic Black')": 38.349998474121094,
  "('Pennsylvania', 'Race/Ethnicity', 'Non-Hispanic White')": 36.83333206176758,
  "('Puerto Rico', 'Age (years)', '65 or older')": 47.5,
  "('Puerto Rico', 'Education', 'Some college or technical school')": 53.400001525878906,
  "('Puerto Rico', 'Income', '$15,000 - $24,999')": 52.54999923706055,
  "('Puerto Rico', 'Income', '$25,000 - $34,999')": 54.900001525878906,
  "('Puerto Rico', 'Income', '$35,000 - $49,999')": 52.5,
  "('Puerto Rico', 'Income', '$50,000 - $74,999')": 52.5,
  "('Puerto Rico', 'Income', 'Less than $15,000')": 56.900001525878906,
  "('Puerto Rico', 'Race/Ethnicity', '2 or more races')": 39.70000076293945,
  "('Puerto Rico', 'Race/Ethnicity', 'Asian')": 39.70000076293945,
  "('Puerto Rico', 'Race/Ethnicity', 'Hispanic')": 51.099998474121094,
  "('Puerto Rico', 'Race/Ethnicity', 'Non-Hispanic White')": 39.70000076293945,
  "('Rhode Island', 'Age (years)', '18 - 24')": 42.099998474121094,
  "('Rhode Island', 'Age (years)', '25 - 34')": 36.900001525878906,
  "('Rhode Island', 'Age (years)', '45 - 54')": 35.400001525878906,
  "('Rhode Island', 'Age (years)', '65 or older')": 30.100000381469727,
  "('Rhode Island', 'Education', 'College graduate')": 29.100000381469727,
  "('Rhode Island', 'Education', 'High school graduate')": 40.599998474121094,
  "('Rhode Island', 'Education', 'Less than high school')": 45.29999923706055,
  "('Rhode Island', 'Gender', 'Male')": 35.099998474121094,
  "('Rhode Island', 'Income', '$35,000 - $49,999')": 31.950000762939453,
  "('Rhode Island', 'Income', '$50,000 - $74,999')": 31.799999237060547,
  "('Rhode Island', 'Income', '$75,000 or greater')": 29.5,
  "('Rhode Island', 'Race/Ethnicity', '2 or more races')": 31.75,
  "('Rhode Island', 'Race/Ethnicity', 'Hawaiian/Pacific Islander')": 39.70000076293945,
  "('Rhode Island', 'Race/Ethnicity', 'Non-Hispanic Black')": 40.29999923706055,
  "('Rhode Island', 'Race/Ethnicity', 'Non-Hispanic White')": 37.29999923706055,
  "('South Carolina', 'Age (years)', '25 - 34')": 44.599998474121094,
  "('South Carolina', 'Age (years)', '45 - 54')": 45.20000076293945,
  "('South Carolina', 'Age (years)', '55 - 64')": 45.400001525878906,
  "('South Carolina', 'Age (years)', '65 or older')": 38.29999923706055,
  "('South Carolina', 'Education', 'High school graduate')": 45.70000076293945,
  "('South Carolina', 'Education', 'Less than high school')": 49.099998474121094,
  "('South Carolina', 'Gender', 'Female')": 40.099998474121094,
  "('South Carolina', 'Income', '$25,000 - $34,999')": 42.0,
  "('South Carolina', 'Income', '$35,000 - $49,999')": 45.400001525878906,
  "('South Carolina', 'Income', '$75,000 or greater')": 36.0,
  "('South Carolina', 'Race/Ethnicity', '2 or more races')": 40.900001525878906,
  "('South Carolina', 'Race/Ethnicity', 'Hawaiian/Pacific Islander')": 39.70000076293945,
  "('South Dakota', 'Age (years)', '18 - 24')": 44.5,
  "('South Dakota', 'Age (years)', '35 - 44')": 42.5,
  "('South Dakota', 'Age (years)', '45 - 54')": 48.70000076293945,
  "('South Dakota', 'Education', 'High school graduate')": 42.5,
  "('South Dakota', 'Gender', 'Female')": 33.29999923706055,
  "('South Dakota', 'Income', '$75,000 or greater')": 38.5,
  "('South Dakota', 'Income', 'Less than $15,000')": 41.0,
  "('South Dakota', 'Race/Ethnicity', 'Non-Hispanic Black')": 39.70000076293945,
  "('South Dakota', 'Race/Ethnicity', 'Non-Hispanic White')": 40.80000305175781,
  "('South Dakota', 'Total', 'Total')": 36.900001525878906,
  "('Tennessee', 'Age (years)', '35 - 44')": 41.0,
  "('Tennessee', 'Age (years)', '55 - 64')": 46.29999923706055,
  "('Tennessee', 'Age (years)', '65 or older')": 37.5,
  "('Tennessee', 'Education', 'High school graduate')": 50.70000076293945,
  "('Tennessee', 'Education', 'Less than high school')": 46.599998474121094,
  "('Tennessee', 'Gender', 'Male')": 42.099998474121094,
  "('Tennessee', 'Income', '$15,000 - $24,999')": 45.099998474121094,
  "('Tennessee', 'Income', '$25,000 - $34,999')": 45.0,
  "('Tennessee', 'Income', '$35,000 - $49,999')": 36.29999923706055,
  "('Tennessee', 'Income', '$75,000 or greater')": 39.5,
  "('Tennessee', 'Race/Ethnicity', '2 or more races')": 30.399999618530273,
  "('Tennessee', 'Race/Ethnicity', 'Asian')": 39.70000076293945,
  "('Tennessee', 'Race/Ethnicity', 'Hispanic')": 38.900001525878906,
  "('Tennessee', 'Total', 'Total')": 42.5,
  "('Texas', 'Age (years)', '25 - 34')": 38.29999923706055,
  "('Texas', 'Age (years)', '45 - 54')": 38.400001525878906,
  "('Texas', 'Education', 'College graduate')": 38.29999923706055,
  "('Texas', 'Education', 'Less than high school')": 35.70000076293945,
  "('Texas', 'Education', 'Some college or technical school')": 41.400001525878906,
  "('Texas', 'Gender', 'Male')": 45.099998474121094,
  "('Texas', 'Income', '$25,000 - $34,999')": 42.099998474121094,
  "('Texas', 'Income', '$35,000 - $49,999')": 44.5,
  "('Texas', 'Income', 'Data not reported')": 41.20000076293945,
  "('Texas', 'Race/Ethnicity', '2 or more races')": 41.099998474121094,
  "('Texas', 'Race/Ethnicity', 'American Indian/Alaska Native')": 34.79999923706055,
  "('Texas', 'Race/Ethnicity', 'Hawaiian/Pacific Islander')": 39.70000076293945,
  "('Texas', 'Race/Ethnicity', 'Non-Hispanic White')": 41.0,
  "('Utah', 'Age (years)', '18 - 24')": 42.599998474121094,
  "('Utah', 'Age (years)', '35 - 44')": 30.700000762939453,
  "('Utah', 'Education', 'Less than high school')": 37.0,
  "('Utah', 'Gender', 'Male')": 41.099998474121094,
  "('Utah', 'Income', '$15,000 - $24,999')": 37.900001525878906,
  "('Utah', 'Income', '$75,000 or greater')": 33.5,
  "('Utah', 'Income', 'Data not reported')": 36.0,
  "('Utah', 'Race/Ethnicity', 'Non-Hispanic Black')": 37.79999923706055,
  "('Utah', 'Race/Ethnicity', 'Non-Hispanic White')": 31.799999237060547,
  "('Utah', 'Total', 'Total')": 32.099998474121094,
  "('Vermont', 'Age (years)', '25 - 34')": 35.5,
  "('Vermont', 'Age (years)', '35 - 44')": 31.549999237060547,
  "('Vermont', 'Age (years)', '55 - 64')": 28.899999618530273,
  "('Vermont', 'Education', 'College graduate')": 22.399999618530273,
  "('Vermont', 'Education', 'High school graduate')": 40.83333206176758,
  "('Vermont', 'Education', 'Some college or technical school')": 34.20000076293945,
  "('Vermont', 'Gender', 'Female')": 25.899999618530273,
  "('Vermont', 'Income', '$25,000 - $34,999')": 37.099998474121094,
  "('Vermont', 'Income', '$75,000 or greater')": 31.700000762939453,
  "('Vermont', 'Income', 'Data not reported')": 27.399999618530273,
  "('Vermont', 'Income', 'Less than $15,000')": 42.79999923706055,
  "('Vermont', 'Race/Ethnicity', '2 or more races')": 39.099998474121094,
  "('Vermont', 'Race/Ethnicity', 'Asian')": 39.70000076293945,
  "('Vermont', 'Total', 'Total')": 34.400001525878906,
  "('Virgin Islands', 'Age (years)', '45 - 54')": 41.70000076293945,
  "('Virgin Islands', 'Age (years)', '55 - 64')": 29.399999618530273,
  "('Virgin Islands', 'Education', 'College graduate')": 39.70000076293945,
  "('Virgin Islands', 'Education', 'Less than high school')": 39.70000076293945,
  "('Virgin Islands', 'Income', '$25,000 - $34,999')": 52.79999923706055,
  "('Virgin Islands', 'Income', '$50,000 - $74,999')": 45.099998474121094,
  "('Virgin Islands', 'Income', '$75,000 or greater')": 51.29999923706055,
  "('Virgin Islands', 'Income', 'Data not reported')": 39.70000076293945,
  "('Virgin Islands', 'Income', 'Less than $15,000')": 28.899999618530273,
  "('Virgin Islands', 'Race/Ethnicity', 'Hawaiian/Pacific Islander')": 39.70000076293945,
  "('Virgin Islands', 'Race/Ethnicity', 'Hispanic')": 39.70000076293945,
  "('Virginia', 'Age (years)', '18 - 24')": 38.79999923706055,
  "('Virginia', 'Age (years)', '25 - 34')": 37.29999923706055,
  "('Virginia', 'Age (years)', '35 - 44')": 37.349998474121094,
  "('Virginia', 'Age (years)', '45 - 54')": 41.0,
  "('Virginia', 'Education', 'College graduate')": 27.700000762939453,
  "('Virginia', 'Education', 'High school graduate')": 45.20000076293945,
  "('Virginia', 'Income', '$15,000 - $24,999')": 43.70000076293945,
  "('Virginia', 'Income', '$25,000 - $34,999')": 38.79999923706055,
  "('Virginia', 'Income', '$35,000 - $49,999')": 43.900001525878906,
  "('Virginia', 'Income', '$75,000 or greater')": 33.400001525878906,
  "('Virginia', 'Income', 'Less than $15,000')": 46.099998474121094,
  "('Virginia', 'Race/Ethnicity', 'Asian')": 40.5,
  "('Virginia', 'Race/Ethnicity', 'Hawaiian/Pacific Islander')": 39.70000076293945,
  "('Virginia', 'Race/Ethnicity', 'Non-Hispanic Black')": 41.099998474121094,
  "('Virginia', 'Race/Ethnicity', 'Non-Hispanic White')": 39.70000076293945,
  "('Washington', 'Age (years)', '18 - 24')": 39.55000305175781,
  "('Washington', 'Age (years)', '25 - 34')": 35.75,
  "('Washington', 'Age (years)', '45 - 54')": 37.0,
  "('Washington', 'Education', 'High school graduate')": 39.349998474121094,
  "('Washington', 'Education', 'Less than high school')": 37.599998474121094,
  "('Washington', 'Education', 'Some college or technical school')": 39.099998474121094,
  "('Washington', 'Income', 'Less than $15,000')": 46.400001525878906,
  "('Washington', 'Race/Ethnicity', '2 or more races')": 43.099998474121094,
  "('Washington', 'Race/Ethnicity', 'American Indian/Alaska Native')": 43.79999923706055,
  "('Washington', 'Race/Ethnicity', 'Hawaiian/Pacific Islander')": 53.599998474121094,
  "('Washington', 'Race/Ethnicity', 'Non-Hispanic White')": 34.29999923706055,
  "('Washington', 'Race/Ethnicity', 'Other')": 37.79999923706055,
  "('West Virginia', 'Age (years)', '25 - 34')": 44.599998474121094,
  "('West Virginia', 'Age (years)', '55 - 64')": 47.70000076293945,
  "('West Virginia', 'Education', 'Some college or technical school')": 47.0,
  "('West Virginia', 'Gender', 'Female')": 43.099998474121094,
  "('West Virginia', 'Gender', 'Male')": 46.20000076293945,
  "('West Virginia', 'Income', '$25,000 - $34,999')": 47.5,
  "('West Virginia', 'Income', '$50,000 - $74,999')": 44.0,
  "('West Virginia', 'Race/Ethnicity', 'Asian')": 39.70000076293945,
  "('West Virginia', 'Race/Ethnicity', 'Non-Hispanic Black')": 44.400001525878906,
  "('Wisconsin', 'Age (years)', '18 - 24')": 31.700000762939453,
  "('Wisconsin', 'Age (years)', '55 - 64')": 40.099998474121094,
  "('Wisconsin', 'Age (years)', '65 or older')": 30.5,
  "('Wisconsin', 'Education', 'High school graduate')": 43.70000076293945,
  "('Wisconsin', 'Income', '$15,000 - $24,999')": 38.70000076293945,
  "('Wisconsin', 'Income', '$25,000 - $34,999')": 42.0,
  "('Wisconsin', 'Income', '$35,000 - $49,999')": 40.0,
  "('Wisconsin', 'Income', 'Data not reported')": 36.94999694824219,
  "('Wisconsin', 'Race/Ethnicity', 'Asian')": 27.799999237060547,
  "('Wisconsin', 'Race/Ethnicity', 'Hawaiian/Pacific Islander')": 39.70000076293945,
  "('Wisconsin', 'Race/Ethnicity', 'Non-Hispanic Black')": 58.20000076293945,
  "('Wyoming', 'Age (years)', '25 - 34')": 50.79999923706055,
  "('Wyoming', 'Age (years)', '45 - 54')": 42.5,
  "('Wyoming', 'Age (years)', '55 - 64')": 45.400001525878906,
  "('Wyoming', 'Education', 'Less than high school')": 52.0,
  "('Wyoming', 'Education', 'Some college or technical school')": 41.900001525878906,
  "('Wyoming', 'Gender', 'Female')": 37.25,
  "('Wyoming', 'Income', '$25,000 - $34,999')": 43.70000076293945,
  "('Wyoming', 'Income', '$75,000 or greater')": 31.700000762939453,
  "('Wyoming', 'Income', 'Data not reported')": 41.79999923706055,
  "('Wyoming', 'Income', 'Less than $15,000')": 46.79999923706055,
  "('Wyoming', 'Race/Ethnicity', 'Asian')": 39.70000076293945,
  "('Wyoming', 'Race/Ethnicity', 'Non-Hispanic Black')": 39.70000076293945,
  "('Wyoming', 'Total', 'Total')": 37.70000076293945
}